pycoord.py
pycoord-0.0.4.dist-info/LICENSE
pycoord-0.0.4.dist-info/METADATA
pycoord-0.0.4.dist-info/WHEEL
pycoord-0.0.4.dist-info/top_level.txt
pycoord-0.0.4.dist-info/RECORD
