Metadata-Version: 2.1
Name: pycoord
Version: 0.0.4
Summary: Store and manipulate cartesian coordinates easier
Home-page: https://github.com/KermitPurple/pycoord
Author: KermitPurple (Shane McDonough)
License: MIT
Keywords: 2D coordinate
Platform: UNKNOWN
License-File: LICENSE
